pyastgen/__init__.py
pyastgen/py.typed
pyastgen-0.1.1.dist-info/METADATA
pyastgen-0.1.1.dist-info/WHEEL
pyastgen-0.1.1.dist-info/licenses/LICENSE
pyastgen-0.1.1.dist-info/RECORD
