Metadata-Version: 2.4
Name: pyastgen
Version: 0.1.1
Summary: Python library for generating Python
Author-email: Patrick Gingras <775.pg.12@gmail.com>
License-Expression: Unlicense
License-File: LICENSE
Requires-Python: >=3.13
